{"nm":"Gym-Finished","mn":"","layers":[{"ty":4,"nm":"Line 2","mn":"","sr":1,"st":27.0000009888355,"op":329.000012049143,"ip":66.0000024171533,"hd":false,"cl":"","ln":"","ddd":0,"bm":0,"hasMask":false,"ao":0,"ks":{"a":{"a":0,"k":[0,0,0],"ix":1},"s":{"a":0,"k":[100,100,100],"ix":6},"sk":{"a":0,"k":0},"p":{"a":0,"k":[500,500,0],"ix":2},"sa":{"a":0,"k":0},"o":{"a":0,"k":100,"ix":11},"r":{"a":0,"k":0,"ix":10}},"ef":[],"shapes":[{"ty":"gr","bm":0,"cl":"","ln":"","hd":false,"mn":"ADBE Vector Group","nm":"Shape 1","ix":1,"cix":2,"np":2,"it":[{"ty":"sh","bm":0,"cl":"","ln":"","hd":false,"mn":"ADBE Vector Shape - Group","nm":"Path 1","ix":1,"d":1,"ks":{"a":0,"k":{"c":false,"i":[[0,6.938],[0,0]],"o":[[0,-5.938],[0,0]],"v":[[0.125,-257.938],[0.062,-316.25]]},"ix":2}},{"ty":"st","bm":0,"cl":"","ln":"","hd":false,"mn":"ADBE Vector Graphic - Stroke","nm":"Stroke 1","lc":2,"lj":2,"ml":1,"o":{"a":0,"k":100,"ix":4},"w":{"a":0,"k":10,"ix":5},"d":[],"c":{"a":0,"k":[0.1137,0.7255,0.2392],"ix":3}},{"ty":"tr","a":{"a":0,"k":[0,0],"ix":1},"s":{"a":0,"k":[100,100],"ix":3},"sk":{"a":0,"k":0,"ix":4},"p":{"a":0,"k":[0,0],"ix":2},"r":{"a":0,"k":0,"ix":6},"sa":{"a":0,"k":0,"ix":5},"o":{"a":0,"k":100,"ix":7}}]},{"ty":"tm","bm":0,"cl":"","ln":"","hd":false,"mn":"ADBE Vector Filter - Trim","nm":"Trim Paths 1","ix":2,"e":{"a":1,"k":[{"o":{"x":0.333,"y":0},"i":{"x":0.667,"y":1},"s":[0],"t":70},{"o":{"x":0.167,"y":0.167},"i":{"x":0.833,"y":0.833},"s":[100],"t":84.000003076377}],"ix":2},"o":{"a":0,"k":0,"ix":3},"s":{"a":0,"k":0,"ix":1},"m":1}],"ind":1},{"ty":4,"nm":"Line 3","mn":"","sr":1,"st":37.0000013550708,"op":339.000012415378,"ip":76.0000027833887,"hd":false,"cl":"","ln":"","ddd":0,"bm":0,"hasMask":false,"ao":0,"ks":{"a":{"a":0,"k":[0,0,0],"ix":1},"s":{"a":0,"k":[100,100,100],"ix":6},"sk":{"a":0,"k":0},"p":{"a":0,"k":[500,500,0],"ix":2},"sa":{"a":0,"k":0},"o":{"a":0,"k":100,"ix":11},"r":{"a":0,"k":0,"ix":10}},"ef":[],"shapes":[{"ty":"gr","bm":0,"cl":"","ln":"","hd":false,"mn":"ADBE Vector Group","nm":"Shape 1","ix":1,"cix":2,"np":2,"it":[{"ty":"sh","bm":0,"cl":"","ln":"","hd":false,"mn":"ADBE Vector Shape - Group","nm":"Path 1","ix":1,"d":1,"ks":{"a":0,"k":{"c":false,"i":[[0,6.938],[0,0]],"o":[[0,-5.938],[0,0]],"v":[[0.125,-257.938],[0.062,-316.25]]},"ix":2}},{"ty":"st","bm":0,"cl":"","ln":"","hd":false,"mn":"ADBE Vector Graphic - Stroke","nm":"Stroke 1","lc":2,"lj":2,"ml":1,"o":{"a":0,"k":100,"ix":4},"w":{"a":0,"k":10,"ix":5},"d":[],"c":{"a":0,"k":[0.1137,0.7255,0.2392],"ix":3}},{"ty":"tr","a":{"a":0,"k":[0,0],"ix":1},"s":{"a":0,"k":[100,100],"ix":3},"sk":{"a":0,"k":0,"ix":4},"p":{"a":0,"k":[0,0],"ix":2},"r":{"a":0,"k":0,"ix":6},"sa":{"a":0,"k":0,"ix":5},"o":{"a":0,"k":100,"ix":7}}]},{"ty":"tm","bm":0,"cl":"","ln":"","hd":false,"mn":"ADBE Vector Filter - Trim","nm":"Trim Paths 1","ix":2,"e":{"a":1,"k":[{"o":{"x":0.333,"y":0},"i":{"x":0.667,"y":1},"s":[0],"t":80},{"o":{"x":0.167,"y":0.167},"i":{"x":0.833,"y":0.833},"s":[100],"t":94.0000034426123}],"ix":2},"o":{"a":0,"k":0,"ix":3},"s":{"a":0,"k":0,"ix":1},"m":1}],"ind":2},{"ty":4,"nm":"Line 4","mn":"","sr":1,"st":46.0000016846826,"op":348.00001274499,"ip":85.0000031130005,"hd":false,"cl":"","ln":"","ddd":0,"bm":0,"hasMask":false,"ao":0,"ks":{"a":{"a":0,"k":[0,0,0],"ix":1},"s":{"a":0,"k":[100,100,100],"ix":6},"sk":{"a":0,"k":0},"p":{"a":0,"k":[500,500,0],"ix":2},"sa":{"a":0,"k":0},"o":{"a":0,"k":100,"ix":11},"r":{"a":0,"k":0,"ix":10}},"ef":[],"shapes":[{"ty":"gr","bm":0,"cl":"","ln":"","hd":false,"mn":"ADBE Vector Group","nm":"Shape 1","ix":1,"cix":2,"np":2,"it":[{"ty":"sh","bm":0,"cl":"","ln":"","hd":false,"mn":"ADBE Vector Shape - Group","nm":"Path 1","ix":1,"d":1,"ks":{"a":0,"k":{"c":false,"i":[[0,6.938],[0,0]],"o":[[0,-5.938],[0,0]],"v":[[0.125,-257.938],[0.062,-316.25]]},"ix":2}},{"ty":"st","bm":0,"cl":"","ln":"","hd":false,"mn":"ADBE Vector Graphic - Stroke","nm":"Stroke 1","lc":2,"lj":2,"ml":1,"o":{"a":0,"k":100,"ix":4},"w":{"a":0,"k":10,"ix":5},"d":[],"c":{"a":0,"k":[0.1137,0.7255,0.2392],"ix":3}},{"ty":"tr","a":{"a":0,"k":[0,0],"ix":1},"s":{"a":0,"k":[100,100],"ix":3},"sk":{"a":0,"k":0,"ix":4},"p":{"a":0,"k":[0,0],"ix":2},"r":{"a":0,"k":0,"ix":6},"sa":{"a":0,"k":0,"ix":5},"o":{"a":0,"k":100,"ix":7}}]},{"ty":"tm","bm":0,"cl":"","ln":"","hd":false,"mn":"ADBE Vector Filter - Trim","nm":"Trim Paths 1","ix":2,"e":{"a":1,"k":[{"o":{"x":0.333,"y":0},"i":{"x":0.667,"y":1},"s":[0],"t":89},{"o":{"x":0.167,"y":0.167},"i":{"x":0.833,"y":0.833},"s":[100],"t":103.000003772224}],"ix":2},"o":{"a":0,"k":0,"ix":3},"s":{"a":0,"k":0,"ix":1},"m":1}],"ind":3},{"ty":4,"nm":"Line 5","mn":"","sr":1,"st":55.0000020142944,"op":357.000013074602,"ip":94.0000034426123,"hd":false,"cl":"","ln":"","ddd":0,"bm":0,"hasMask":false,"ao":0,"ks":{"a":{"a":0,"k":[0,0,0],"ix":1},"s":{"a":0,"k":[100,100,100],"ix":6},"sk":{"a":0,"k":0},"p":{"a":0,"k":[500,500,0],"ix":2},"sa":{"a":0,"k":0},"o":{"a":0,"k":100,"ix":11},"r":{"a":0,"k":0,"ix":10}},"ef":[],"shapes":[{"ty":"gr","bm":0,"cl":"","ln":"","hd":false,"mn":"ADBE Vector Group","nm":"Shape 1","ix":1,"cix":2,"np":2,"it":[{"ty":"sh","bm":0,"cl":"","ln":"","hd":false,"mn":"ADBE Vector Shape - Group","nm":"Path 1","ix":1,"d":1,"ks":{"a":0,"k":{"c":false,"i":[[0,6.938],[0,0]],"o":[[0,-5.938],[0,0]],"v":[[0.125,-257.938],[0.062,-316.25]]},"ix":2}},{"ty":"st","bm":0,"cl":"","ln":"","hd":false,"mn":"ADBE Vector Graphic - Stroke","nm":"Stroke 1","lc":2,"lj":2,"ml":1,"o":{"a":0,"k":100,"ix":4},"w":{"a":0,"k":10,"ix":5},"d":[],"c":{"a":0,"k":[0.1137,0.7255,0.2392],"ix":3}},{"ty":"tr","a":{"a":0,"k":[0,0],"ix":1},"s":{"a":0,"k":[100,100],"ix":3},"sk":{"a":0,"k":0,"ix":4},"p":{"a":0,"k":[0,0],"ix":2},"r":{"a":0,"k":0,"ix":6},"sa":{"a":0,"k":0,"ix":5},"o":{"a":0,"k":100,"ix":7}}]},{"ty":"tm","bm":0,"cl":"","ln":"","hd":false,"mn":"ADBE Vector Filter - Trim","nm":"Trim Paths 1","ix":2,"e":{"a":1,"k":[{"o":{"x":0.333,"y":0},"i":{"x":0.667,"y":1},"s":[0],"t":98},{"o":{"x":0.167,"y":0.167},"i":{"x":0.833,"y":0.833},"s":[100],"t":112.000004101836}],"ix":2},"o":{"a":0,"k":0,"ix":3},"s":{"a":0,"k":0,"ix":1},"m":1}],"ind":4},{"ty":4,"nm":"Line 6","mn":"","sr":1,"st":65.0000023805298,"op":367.000013440837,"ip":104.000003808848,"hd":false,"cl":"","ln":"","ddd":0,"bm":0,"hasMask":false,"ao":0,"ks":{"a":{"a":0,"k":[0,0,0],"ix":1},"s":{"a":0,"k":[100,100,100],"ix":6},"sk":{"a":0,"k":0},"p":{"a":0,"k":[500,500,0],"ix":2},"sa":{"a":0,"k":0},"o":{"a":0,"k":100,"ix":11},"r":{"a":0,"k":0,"ix":10}},"ef":[],"shapes":[{"ty":"gr","bm":0,"cl":"","ln":"","hd":false,"mn":"ADBE Vector Group","nm":"Shape 1","ix":1,"cix":2,"np":2,"it":[{"ty":"sh","bm":0,"cl":"","ln":"","hd":false,"mn":"ADBE Vector Shape - Group","nm":"Path 1","ix":1,"d":1,"ks":{"a":0,"k":{"c":false,"i":[[0,6.938],[0,0]],"o":[[0,-5.938],[0,0]],"v":[[0.125,-257.938],[0.062,-316.25]]},"ix":2}},{"ty":"st","bm":0,"cl":"","ln":"","hd":false,"mn":"ADBE Vector Graphic - Stroke","nm":"Stroke 1","lc":2,"lj":2,"ml":1,"o":{"a":0,"k":100,"ix":4},"w":{"a":0,"k":10,"ix":5},"d":[],"c":{"a":0,"k":[0.1137,0.7255,0.2392],"ix":3}},{"ty":"tr","a":{"a":0,"k":[0,0],"ix":1},"s":{"a":0,"k":[100,100],"ix":3},"sk":{"a":0,"k":0,"ix":4},"p":{"a":0,"k":[0,0],"ix":2},"r":{"a":0,"k":0,"ix":6},"sa":{"a":0,"k":0,"ix":5},"o":{"a":0,"k":100,"ix":7}}]},{"ty":"tm","bm":0,"cl":"","ln":"","hd":false,"mn":"ADBE Vector Filter - Trim","nm":"Trim Paths 1","ix":2,"e":{"a":1,"k":[{"o":{"x":0.333,"y":0},"i":{"x":0.667,"y":1},"s":[0],"t":108},{"o":{"x":0.167,"y":0.167},"i":{"x":0.833,"y":0.833},"s":[100],"t":122.000004468071}],"ix":2},"o":{"a":0,"k":0,"ix":3},"s":{"a":0,"k":0,"ix":1},"m":1}],"ind":5},{"ty":4,"nm":"Line 7","mn":"","sr":1,"st":74.0000027101416,"op":376.000013770449,"ip":113.00000413846,"hd":false,"cl":"","ln":"","ddd":0,"bm":0,"hasMask":false,"ao":0,"ks":{"a":{"a":0,"k":[0,0,0],"ix":1},"s":{"a":0,"k":[100,100,100],"ix":6},"sk":{"a":0,"k":0},"p":{"a":0,"k":[500,500,0],"ix":2},"sa":{"a":0,"k":0},"o":{"a":0,"k":100,"ix":11},"r":{"a":0,"k":0,"ix":10}},"ef":[],"shapes":[{"ty":"gr","bm":0,"cl":"","ln":"","hd":false,"mn":"ADBE Vector Group","nm":"Shape 1","ix":1,"cix":2,"np":2,"it":[{"ty":"sh","bm":0,"cl":"","ln":"","hd":false,"mn":"ADBE Vector Shape - Group","nm":"Path 1","ix":1,"d":1,"ks":{"a":0,"k":{"c":false,"i":[[0,6.938],[0,0]],"o":[[0,-5.938],[0,0]],"v":[[0.125,-257.938],[0.062,-316.25]]},"ix":2}},{"ty":"st","bm":0,"cl":"","ln":"","hd":false,"mn":"ADBE Vector Graphic - Stroke","nm":"Stroke 1","lc":2,"lj":2,"ml":1,"o":{"a":0,"k":100,"ix":4},"w":{"a":0,"k":10,"ix":5},"d":[],"c":{"a":0,"k":[0.1137,0.7255,0.2392],"ix":3}},{"ty":"tr","a":{"a":0,"k":[0,0],"ix":1},"s":{"a":0,"k":[100,100],"ix":3},"sk":{"a":0,"k":0,"ix":4},"p":{"a":0,"k":[0,0],"ix":2},"r":{"a":0,"k":0,"ix":6},"sa":{"a":0,"k":0,"ix":5},"o":{"a":0,"k":100,"ix":7}}]},{"ty":"tm","bm":0,"cl":"","ln":"","hd":false,"mn":"ADBE Vector Filter - Trim","nm":"Trim Paths 1","ix":2,"e":{"a":1,"k":[{"o":{"x":0.333,"y":0},"i":{"x":0.667,"y":1},"s":[0],"t":117},{"o":{"x":0.167,"y":0.167},"i":{"x":0.833,"y":0.833},"s":[100],"t":131.000004797683}],"ix":2},"o":{"a":0,"k":0,"ix":3},"s":{"a":0,"k":0,"ix":1},"m":1}],"ind":6},{"ty":4,"nm":"Line 8","mn":"","sr":1,"st":83.0000030397534,"op":385.000014100061,"ip":122.000004468071,"hd":false,"cl":"","ln":"","ddd":0,"bm":0,"hasMask":false,"ao":0,"ks":{"a":{"a":0,"k":[0,0,0],"ix":1},"s":{"a":0,"k":[100,100,100],"ix":6},"sk":{"a":0,"k":0},"p":{"a":0,"k":[500,500,0],"ix":2},"sa":{"a":0,"k":0},"o":{"a":0,"k":100,"ix":11},"r":{"a":0,"k":0,"ix":10}},"ef":[],"shapes":[{"ty":"gr","bm":0,"cl":"","ln":"","hd":false,"mn":"ADBE Vector Group","nm":"Shape 1","ix":1,"cix":2,"np":2,"it":[{"ty":"sh","bm":0,"cl":"","ln":"","hd":false,"mn":"ADBE Vector Shape - Group","nm":"Path 1","ix":1,"d":1,"ks":{"a":0,"k":{"c":false,"i":[[0,6.938],[0,0]],"o":[[0,-5.938],[0,0]],"v":[[0.125,-257.938],[0.062,-316.25]]},"ix":2}},{"ty":"st","bm":0,"cl":"","ln":"","hd":false,"mn":"ADBE Vector Graphic - Stroke","nm":"Stroke 1","lc":2,"lj":2,"ml":1,"o":{"a":0,"k":100,"ix":4},"w":{"a":0,"k":10,"ix":5},"d":[],"c":{"a":0,"k":[0.1137,0.7255,0.2392],"ix":3}},{"ty":"tr","a":{"a":0,"k":[0,0],"ix":1},"s":{"a":0,"k":[100,100],"ix":3},"sk":{"a":0,"k":0,"ix":4},"p":{"a":0,"k":[0,0],"ix":2},"r":{"a":0,"k":0,"ix":6},"sa":{"a":0,"k":0,"ix":5},"o":{"a":0,"k":100,"ix":7}}]},{"ty":"tm","bm":0,"cl":"","ln":"","hd":false,"mn":"ADBE Vector Filter - Trim","nm":"Trim Paths 1","ix":2,"e":{"a":1,"k":[{"o":{"x":0.333,"y":0},"i":{"x":0.667,"y":1},"s":[0],"t":126},{"o":{"x":0.167,"y":0.167},"i":{"x":0.833,"y":0.833},"s":[100],"t":140.000005127295}],"ix":2},"o":{"a":0,"k":0,"ix":3},"s":{"a":0,"k":0,"ix":1},"m":1}],"ind":7},{"ty":4,"nm":"Line 9","mn":"","sr":1,"st":91.0000033327417,"op":393.000014393049,"ip":130.00000476106,"hd":false,"cl":"","ln":"","ddd":0,"bm":0,"hasMask":false,"ao":0,"ks":{"a":{"a":0,"k":[0,0,0],"ix":1},"s":{"a":0,"k":[100,100,100],"ix":6},"sk":{"a":0,"k":0},"p":{"a":0,"k":[500,500,0],"ix":2},"sa":{"a":0,"k":0},"o":{"a":0,"k":100,"ix":11},"r":{"a":0,"k":0,"ix":10}},"ef":[],"shapes":[{"ty":"gr","bm":0,"cl":"","ln":"","hd":false,"mn":"ADBE Vector Group","nm":"Shape 1","ix":1,"cix":2,"np":2,"it":[{"ty":"sh","bm":0,"cl":"","ln":"","hd":false,"mn":"ADBE Vector Shape - Group","nm":"Path 1","ix":1,"d":1,"ks":{"a":0,"k":{"c":false,"i":[[0,6.938],[0,0]],"o":[[0,-5.938],[0,0]],"v":[[0.125,-257.938],[0.062,-316.25]]},"ix":2}},{"ty":"st","bm":0,"cl":"","ln":"","hd":false,"mn":"ADBE Vector Graphic - Stroke","nm":"Stroke 1","lc":2,"lj":2,"ml":1,"o":{"a":0,"k":100,"ix":4},"w":{"a":0,"k":10,"ix":5},"d":[],"c":{"a":0,"k":[0.1137,0.7255,0.2392],"ix":3}},{"ty":"tr","a":{"a":0,"k":[0,0],"ix":1},"s":{"a":0,"k":[100,100],"ix":3},"sk":{"a":0,"k":0,"ix":4},"p":{"a":0,"k":[0,0],"ix":2},"r":{"a":0,"k":0,"ix":6},"sa":{"a":0,"k":0,"ix":5},"o":{"a":0,"k":100,"ix":7}}]},{"ty":"tm","bm":0,"cl":"","ln":"","hd":false,"mn":"ADBE Vector Filter - Trim","nm":"Trim Paths 1","ix":2,"e":{"a":1,"k":[{"o":{"x":0.333,"y":0},"i":{"x":0.667,"y":1},"s":[0],"t":134},{"o":{"x":0.167,"y":0.167},"i":{"x":0.833,"y":0.833},"s":[100],"t":148.000005420283}],"ix":2},"o":{"a":0,"k":0,"ix":3},"s":{"a":0,"k":0,"ix":1},"m":1}],"ind":8},{"ty":4,"nm":"Line 10","mn":"","sr":1,"st":100.000003662354,"op":402.000014722661,"ip":139.000005090671,"hd":false,"cl":"","ln":"","ddd":0,"bm":0,"hasMask":false,"ao":0,"ks":{"a":{"a":0,"k":[0,0,0],"ix":1},"s":{"a":0,"k":[100,100,100],"ix":6},"sk":{"a":0,"k":0},"p":{"a":0,"k":[500,500,0],"ix":2},"sa":{"a":0,"k":0},"o":{"a":0,"k":100,"ix":11},"r":{"a":0,"k":0,"ix":10}},"ef":[],"shapes":[{"ty":"gr","bm":0,"cl":"","ln":"","hd":false,"mn":"ADBE Vector Group","nm":"Shape 1","ix":1,"cix":2,"np":2,"it":[{"ty":"sh","bm":0,"cl":"","ln":"","hd":false,"mn":"ADBE Vector Shape - Group","nm":"Path 1","ix":1,"d":1,"ks":{"a":0,"k":{"c":false,"i":[[0,6.938],[0,0]],"o":[[0,-5.938],[0,0]],"v":[[0.125,-257.938],[0.062,-316.25]]},"ix":2}},{"ty":"st","bm":0,"cl":"","ln":"","hd":false,"mn":"ADBE Vector Graphic - Stroke","nm":"Stroke 1","lc":2,"lj":2,"ml":1,"o":{"a":0,"k":100,"ix":4},"w":{"a":0,"k":10,"ix":5},"d":[],"c":{"a":0,"k":[0.1137,0.7255,0.2392],"ix":3}},{"ty":"tr","a":{"a":0,"k":[0,0],"ix":1},"s":{"a":0,"k":[100,100],"ix":3},"sk":{"a":0,"k":0,"ix":4},"p":{"a":0,"k":[0,0],"ix":2},"r":{"a":0,"k":0,"ix":6},"sa":{"a":0,"k":0,"ix":5},"o":{"a":0,"k":100,"ix":7}}]},{"ty":"tm","bm":0,"cl":"","ln":"","hd":false,"mn":"ADBE Vector Filter - Trim","nm":"Trim Paths 1","ix":2,"e":{"a":1,"k":[{"o":{"x":0.333,"y":0},"i":{"x":0.667,"y":1},"s":[0],"t":143},{"o":{"x":0.167,"y":0.167},"i":{"x":0.833,"y":0.833},"s":[100],"t":157.000005749895}],"ix":2},"o":{"a":0,"k":0,"ix":3},"s":{"a":0,"k":0,"ix":1},"m":1}],"ind":9},{"ty":4,"nm":"Line 11","mn":"","sr":1,"st":107.000003918718,"op":409.000014979026,"ip":146.000005347036,"hd":false,"cl":"","ln":"","ddd":0,"bm":0,"hasMask":false,"ao":0,"ks":{"a":{"a":0,"k":[0,0,0],"ix":1},"s":{"a":0,"k":[100,100,100],"ix":6},"sk":{"a":0,"k":0},"p":{"a":0,"k":[500,500,0],"ix":2},"sa":{"a":0,"k":0},"o":{"a":0,"k":100,"ix":11},"r":{"a":0,"k":0,"ix":10}},"ef":[],"shapes":[{"ty":"gr","bm":0,"cl":"","ln":"","hd":false,"mn":"ADBE Vector Group","nm":"Shape 1","ix":1,"cix":2,"np":2,"it":[{"ty":"sh","bm":0,"cl":"","ln":"","hd":false,"mn":"ADBE Vector Shape - Group","nm":"Path 1","ix":1,"d":1,"ks":{"a":0,"k":{"c":false,"i":[[0,6.938],[0,0]],"o":[[0,-5.938],[0,0]],"v":[[0.125,-257.938],[0.062,-316.25]]},"ix":2}},{"ty":"st","bm":0,"cl":"","ln":"","hd":false,"mn":"ADBE Vector Graphic - Stroke","nm":"Stroke 1","lc":2,"lj":2,"ml":1,"o":{"a":0,"k":100,"ix":4},"w":{"a":0,"k":10,"ix":5},"d":[],"c":{"a":0,"k":[0.1137,0.7255,0.2392],"ix":3}},{"ty":"tr","a":{"a":0,"k":[0,0],"ix":1},"s":{"a":0,"k":[100,100],"ix":3},"sk":{"a":0,"k":0,"ix":4},"p":{"a":0,"k":[0,0],"ix":2},"r":{"a":0,"k":0,"ix":6},"sa":{"a":0,"k":0,"ix":5},"o":{"a":0,"k":100,"ix":7}}]},{"ty":"tm","bm":0,"cl":"","ln":"","hd":false,"mn":"ADBE Vector Filter - Trim","nm":"Trim Paths 1","ix":2,"e":{"a":1,"k":[{"o":{"x":0.333,"y":0},"i":{"x":0.667,"y":1},"s":[0],"t":150},{"o":{"x":0.167,"y":0.167},"i":{"x":0.833,"y":0.833},"s":[100],"t":164.00000600626}],"ix":2},"o":{"a":0,"k":0,"ix":3},"s":{"a":0,"k":0,"ix":1},"m":1}],"ind":10},{"ty":4,"nm":"Line 12","mn":"","sr":1,"st":115.000004211707,"op":417.000015272014,"ip":154.000005640024,"hd":false,"cl":"","ln":"","ddd":0,"bm":0,"hasMask":false,"ao":0,"ks":{"a":{"a":0,"k":[0,0,0],"ix":1},"s":{"a":0,"k":[100,100,100],"ix":6},"sk":{"a":0,"k":0},"p":{"a":0,"k":[500,500,0],"ix":2},"sa":{"a":0,"k":0},"o":{"a":0,"k":100,"ix":11},"r":{"a":0,"k":0,"ix":10}},"ef":[],"shapes":[{"ty":"gr","bm":0,"cl":"","ln":"","hd":false,"mn":"ADBE Vector Group","nm":"Shape 1","ix":1,"cix":2,"np":2,"it":[{"ty":"sh","bm":0,"cl":"","ln":"","hd":false,"mn":"ADBE Vector Shape - Group","nm":"Path 1","ix":1,"d":1,"ks":{"a":0,"k":{"c":false,"i":[[0,6.938],[0,0]],"o":[[0,-5.938],[0,0]],"v":[[0.125,-257.938],[0.062,-316.25]]},"ix":2}},{"ty":"st","bm":0,"cl":"","ln":"","hd":false,"mn":"ADBE Vector Graphic - Stroke","nm":"Stroke 1","lc":2,"lj":2,"ml":1,"o":{"a":0,"k":100,"ix":4},"w":{"a":0,"k":10,"ix":5},"d":[],"c":{"a":0,"k":[0.1137,0.7255,0.2392],"ix":3}},{"ty":"tr","a":{"a":0,"k":[0,0],"ix":1},"s":{"a":0,"k":[100,100],"ix":3},"sk":{"a":0,"k":0,"ix":4},"p":{"a":0,"k":[0,0],"ix":2},"r":{"a":0,"k":0,"ix":6},"sa":{"a":0,"k":0,"ix":5},"o":{"a":0,"k":100,"ix":7}}]},{"ty":"tm","bm":0,"cl":"","ln":"","hd":false,"mn":"ADBE Vector Filter - Trim","nm":"Trim Paths 1","ix":2,"e":{"a":1,"k":[{"o":{"x":0.333,"y":0},"i":{"x":0.667,"y":1},"s":[0],"t":158},{"o":{"x":0.167,"y":0.167},"i":{"x":0.833,"y":0.833},"s":[100],"t":172.000006299248}],"ix":2},"o":{"a":0,"k":0,"ix":3},"s":{"a":0,"k":0,"ix":1},"m":1}],"ind":11},{"ty":4,"nm":"Line 13","mn":"","sr":1,"st":122.000004468071,"op":424.000015528379,"ip":161.000005896389,"hd":false,"cl":"","ln":"","ddd":0,"bm":0,"hasMask":false,"ao":0,"ks":{"a":{"a":0,"k":[0,0,0],"ix":1},"s":{"a":0,"k":[100,100,100],"ix":6},"sk":{"a":0,"k":0},"p":{"a":0,"k":[500,500,0],"ix":2},"sa":{"a":0,"k":0},"o":{"a":0,"k":100,"ix":11},"r":{"a":0,"k":0,"ix":10}},"ef":[],"shapes":[{"ty":"gr","bm":0,"cl":"","ln":"","hd":false,"mn":"ADBE Vector Group","nm":"Shape 1","ix":1,"cix":2,"np":2,"it":[{"ty":"sh","bm":0,"cl":"","ln":"","hd":false,"mn":"ADBE Vector Shape - Group","nm":"Path 1","ix":1,"d":1,"ks":{"a":0,"k":{"c":false,"i":[[0,6.938],[0,0]],"o":[[0,-5.938],[0,0]],"v":[[0.125,-257.938],[0.062,-316.25]]},"ix":2}},{"ty":"st","bm":0,"cl":"","ln":"","hd":false,"mn":"ADBE Vector Graphic - Stroke","nm":"Stroke 1","lc":2,"lj":2,"ml":1,"o":{"a":0,"k":100,"ix":4},"w":{"a":0,"k":10,"ix":5},"d":[],"c":{"a":0,"k":[0.1137,0.7255,0.2392],"ix":3}},{"ty":"tr","a":{"a":0,"k":[0,0],"ix":1},"s":{"a":0,"k":[100,100],"ix":3},"sk":{"a":0,"k":0,"ix":4},"p":{"a":0,"k":[0,0],"ix":2},"r":{"a":0,"k":0,"ix":6},"sa":{"a":0,"k":0,"ix":5},"o":{"a":0,"k":100,"ix":7}}]},{"ty":"tm","bm":0,"cl":"","ln":"","hd":false,"mn":"ADBE Vector Filter - Trim","nm":"Trim Paths 1","ix":2,"e":{"a":1,"k":[{"o":{"x":0.333,"y":0},"i":{"x":0.667,"y":1},"s":[0],"t":165},{"o":{"x":0.167,"y":0.167},"i":{"x":0.833,"y":0.833},"s":[100],"t":179.000006555613}],"ix":2},"o":{"a":0,"k":0,"ix":3},"s":{"a":0,"k":0,"ix":1},"m":1}],"ind":12},{"ty":4,"nm":"Line 14","mn":"","sr":1,"st":128.000004687813,"op":430.00001574812,"ip":167.00000611613,"hd":false,"cl":"","ln":"","ddd":0,"bm":0,"hasMask":false,"ao":0,"ks":{"a":{"a":0,"k":[0,0,0],"ix":1},"s":{"a":0,"k":[100,100,100],"ix":6},"sk":{"a":0,"k":0},"p":{"a":0,"k":[500,500,0],"ix":2},"sa":{"a":0,"k":0},"o":{"a":0,"k":100,"ix":11},"r":{"a":0,"k":0,"ix":10}},"ef":[],"shapes":[{"ty":"gr","bm":0,"cl":"","ln":"","hd":false,"mn":"ADBE Vector Group","nm":"Shape 1","ix":1,"cix":2,"np":2,"it":[{"ty":"sh","bm":0,"cl":"","ln":"","hd":false,"mn":"ADBE Vector Shape - Group","nm":"Path 1","ix":1,"d":1,"ks":{"a":0,"k":{"c":false,"i":[[0,6.938],[0,0]],"o":[[0,-5.938],[0,0]],"v":[[0.125,-257.938],[0.062,-316.25]]},"ix":2}},{"ty":"st","bm":0,"cl":"","ln":"","hd":false,"mn":"ADBE Vector Graphic - Stroke","nm":"Stroke 1","lc":2,"lj":2,"ml":1,"o":{"a":0,"k":100,"ix":4},"w":{"a":0,"k":10,"ix":5},"d":[],"c":{"a":0,"k":[0.1137,0.7255,0.2392],"ix":3}},{"ty":"tr","a":{"a":0,"k":[0,0],"ix":1},"s":{"a":0,"k":[100,100],"ix":3},"sk":{"a":0,"k":0,"ix":4},"p":{"a":0,"k":[0,0],"ix":2},"r":{"a":0,"k":0,"ix":6},"sa":{"a":0,"k":0,"ix":5},"o":{"a":0,"k":100,"ix":7}}]},{"ty":"tm","bm":0,"cl":"","ln":"","hd":false,"mn":"ADBE Vector Filter - Trim","nm":"Trim Paths 1","ix":2,"e":{"a":1,"k":[{"o":{"x":0.333,"y":0},"i":{"x":0.667,"y":1},"s":[0],"t":171},{"o":{"x":0.167,"y":0.167},"i":{"x":0.833,"y":0.833},"s":[100],"t":185.000006775354}],"ix":2},"o":{"a":0,"k":0,"ix":3},"s":{"a":0,"k":0,"ix":1},"m":1}],"ind":13},{"ty":4,"nm":"Line 15","mn":"","sr":1,"st":135.000004944177,"op":437.000016004485,"ip":174.000006372495,"hd":false,"cl":"","ln":"","ddd":0,"bm":0,"hasMask":false,"ao":0,"ks":{"a":{"a":0,"k":[0,0,0],"ix":1},"s":{"a":0,"k":[100,100,100],"ix":6},"sk":{"a":0,"k":0},"p":{"a":0,"k":[500,500,0],"ix":2},"sa":{"a":0,"k":0},"o":{"a":0,"k":100,"ix":11},"r":{"a":0,"k":0,"ix":10}},"ef":[],"shapes":[{"ty":"gr","bm":0,"cl":"","ln":"","hd":false,"mn":"ADBE Vector Group","nm":"Shape 1","ix":1,"cix":2,"np":2,"it":[{"ty":"sh","bm":0,"cl":"","ln":"","hd":false,"mn":"ADBE Vector Shape - Group","nm":"Path 1","ix":1,"d":1,"ks":{"a":0,"k":{"c":false,"i":[[0,6.938],[0,0]],"o":[[0,-5.938],[0,0]],"v":[[0.125,-257.938],[0.062,-316.25]]},"ix":2}},{"ty":"st","bm":0,"cl":"","ln":"","hd":false,"mn":"ADBE Vector Graphic - Stroke","nm":"Stroke 1","lc":2,"lj":2,"ml":1,"o":{"a":0,"k":100,"ix":4},"w":{"a":0,"k":10,"ix":5},"d":[],"c":{"a":0,"k":[0.1137,0.7255,0.2392],"ix":3}},{"ty":"tr","a":{"a":0,"k":[0,0],"ix":1},"s":{"a":0,"k":[100,100],"ix":3},"sk":{"a":0,"k":0,"ix":4},"p":{"a":0,"k":[0,0],"ix":2},"r":{"a":0,"k":0,"ix":6},"sa":{"a":0,"k":0,"ix":5},"o":{"a":0,"k":100,"ix":7}}]},{"ty":"tm","bm":0,"cl":"","ln":"","hd":false,"mn":"ADBE Vector Filter - Trim","nm":"Trim Paths 1","ix":2,"e":{"a":1,"k":[{"o":{"x":0.333,"y":0},"i":{"x":0.667,"y":1},"s":[0],"t":178},{"o":{"x":0.167,"y":0.167},"i":{"x":0.833,"y":0.833},"s":[100],"t":192.000007031719}],"ix":2},"o":{"a":0,"k":0,"ix":3},"s":{"a":0,"k":0,"ix":1},"m":1}],"ind":14},{"ty":4,"nm":"Line 16","mn":"","sr":1,"st":147.00000538366,"op":449.000016443967,"ip":186.000006811978,"hd":false,"cl":"","ln":"","ddd":0,"bm":0,"hasMask":false,"ao":0,"ks":{"a":{"a":0,"k":[0,0,0],"ix":1},"s":{"a":0,"k":[100,100,100],"ix":6},"sk":{"a":0,"k":0},"p":{"a":0,"k":[500,500,0],"ix":2},"sa":{"a":0,"k":0},"o":{"a":0,"k":100,"ix":11},"r":{"a":0,"k":0,"ix":10}},"ef":[],"shapes":[{"ty":"gr","bm":0,"cl":"","ln":"","hd":false,"mn":"ADBE Vector Group","nm":"Shape 1","ix":1,"cix":2,"np":2,"it":[{"ty":"sh","bm":0,"cl":"","ln":"","hd":false,"mn":"ADBE Vector Shape - Group","nm":"Path 1","ix":1,"d":1,"ks":{"a":0,"k":{"c":false,"i":[[0,6.938],[0,0]],"o":[[0,-5.938],[0,0]],"v":[[0.125,-257.938],[0.062,-316.25]]},"ix":2}},{"ty":"st","bm":0,"cl":"","ln":"","hd":false,"mn":"ADBE Vector Graphic - Stroke","nm":"Stroke 1","lc":2,"lj":2,"ml":1,"o":{"a":0,"k":100,"ix":4},"w":{"a":0,"k":10,"ix":5},"d":[],"c":{"a":0,"k":[0.1137,0.7255,0.2392],"ix":3}},{"ty":"tr","a":{"a":0,"k":[0,0],"ix":1},"s":{"a":0,"k":[100,100],"ix":3},"sk":{"a":0,"k":0,"ix":4},"p":{"a":0,"k":[0,0],"ix":2},"r":{"a":0,"k":0,"ix":6},"sa":{"a":0,"k":0,"ix":5},"o":{"a":0,"k":100,"ix":7}}]},{"ty":"tm","bm":0,"cl":"","ln":"","hd":false,"mn":"ADBE Vector Filter - Trim","nm":"Trim Paths 1","ix":2,"e":{"a":1,"k":[{"o":{"x":0.333,"y":0},"i":{"x":0.667,"y":1},"s":[0],"t":190},{"o":{"x":0.167,"y":0.167},"i":{"x":0.833,"y":0.833},"s":[100],"t":204.000007471201}],"ix":2},"o":{"a":0,"k":0,"ix":3},"s":{"a":0,"k":0,"ix":1},"m":1}],"ind":15},{"ty":4,"nm":"Line 17","mn":"","sr":1,"st":156.000005713272,"op":458.000016773579,"ip":195.000007141589,"hd":false,"cl":"","ln":"","ddd":0,"bm":0,"hasMask":false,"ao":0,"ks":{"a":{"a":0,"k":[0,0,0],"ix":1},"s":{"a":0,"k":[100,100,100],"ix":6},"sk":{"a":0,"k":0},"p":{"a":0,"k":[500,500,0],"ix":2},"sa":{"a":0,"k":0},"o":{"a":0,"k":100,"ix":11},"r":{"a":0,"k":0,"ix":10}},"ef":[],"shapes":[{"ty":"gr","bm":0,"cl":"","ln":"","hd":false,"mn":"ADBE Vector Group","nm":"Shape 1","ix":1,"cix":2,"np":2,"it":[{"ty":"sh","bm":0,"cl":"","ln":"","hd":false,"mn":"ADBE Vector Shape - Group","nm":"Path 1","ix":1,"d":1,"ks":{"a":0,"k":{"c":false,"i":[[0,6.938],[0,0]],"o":[[0,-5.938],[0,0]],"v":[[0.125,-257.938],[0.062,-316.25]]},"ix":2}},{"ty":"st","bm":0,"cl":"","ln":"","hd":false,"mn":"ADBE Vector Graphic - Stroke","nm":"Stroke 1","lc":2,"lj":2,"ml":1,"o":{"a":0,"k":100,"ix":4},"w":{"a":0,"k":10,"ix":5},"d":[],"c":{"a":0,"k":[0.1137,0.7255,0.2392],"ix":3}},{"ty":"tr","a":{"a":0,"k":[0,0],"ix":1},"s":{"a":0,"k":[100,100],"ix":3},"sk":{"a":0,"k":0,"ix":4},"p":{"a":0,"k":[0,0],"ix":2},"r":{"a":0,"k":0,"ix":6},"sa":{"a":0,"k":0,"ix":5},"o":{"a":0,"k":100,"ix":7}}]},{"ty":"tm","bm":0,"cl":"","ln":"","hd":false,"mn":"ADBE Vector Filter - Trim","nm":"Trim Paths 1","ix":2,"e":{"a":1,"k":[{"o":{"x":0.333,"y":0},"i":{"x":0.667,"y":1},"s":[0],"t":199},{"o":{"x":0.167,"y":0.167},"i":{"x":0.833,"y":0.833},"s":[100],"t":213.000007800813}],"ix":2},"o":{"a":0,"k":0,"ix":3},"s":{"a":0,"k":0,"ix":1},"m":1}],"ind":16},{"ty":4,"nm":"Line 18","mn":"","sr":1,"st":167.00000611613,"op":469.000017176438,"ip":206.000007544448,"hd":false,"cl":"","ln":"","ddd":0,"bm":0,"hasMask":false,"ao":0,"ks":{"a":{"a":0,"k":[0,0,0],"ix":1},"s":{"a":0,"k":[100,100,100],"ix":6},"sk":{"a":0,"k":0},"p":{"a":0,"k":[500,500,0],"ix":2},"sa":{"a":0,"k":0},"o":{"a":0,"k":100,"ix":11},"r":{"a":0,"k":0,"ix":10}},"ef":[],"shapes":[{"ty":"gr","bm":0,"cl":"","ln":"","hd":false,"mn":"ADBE Vector Group","nm":"Shape 1","ix":1,"cix":2,"np":2,"it":[{"ty":"sh","bm":0,"cl":"","ln":"","hd":false,"mn":"ADBE Vector Shape - Group","nm":"Path 1","ix":1,"d":1,"ks":{"a":0,"k":{"c":false,"i":[[0,6.938],[0,0]],"o":[[0,-5.938],[0,0]],"v":[[0.125,-257.938],[0.062,-316.25]]},"ix":2}},{"ty":"st","bm":0,"cl":"","ln":"","hd":false,"mn":"ADBE Vector Graphic - Stroke","nm":"Stroke 1","lc":2,"lj":2,"ml":1,"o":{"a":0,"k":100,"ix":4},"w":{"a":0,"k":10,"ix":5},"d":[],"c":{"a":0,"k":[0.1137,0.7255,0.2392],"ix":3}},{"ty":"tr","a":{"a":0,"k":[0,0],"ix":1},"s":{"a":0,"k":[100,100],"ix":3},"sk":{"a":0,"k":0,"ix":4},"p":{"a":0,"k":[0,0],"ix":2},"r":{"a":0,"k":0,"ix":6},"sa":{"a":0,"k":0,"ix":5},"o":{"a":0,"k":100,"ix":7}}]},{"ty":"tm","bm":0,"cl":"","ln":"","hd":false,"mn":"ADBE Vector Filter - Trim","nm":"Trim Paths 1","ix":2,"e":{"a":1,"k":[{"o":{"x":0.333,"y":0},"i":{"x":0.667,"y":1},"s":[0],"t":210},{"o":{"x":0.167,"y":0.167},"i":{"x":0.833,"y":0.833},"s":[100],"t":224.000008203672}],"ix":2},"o":{"a":0,"k":0,"ix":3},"s":{"a":0,"k":0,"ix":1},"m":1}],"ind":17},{"ty":4,"nm":"Line 19","mn":"","sr":1,"st":177.000006482366,"op":479.000017542673,"ip":216.000007910684,"hd":false,"cl":"","ln":"","ddd":0,"bm":0,"hasMask":false,"ao":0,"ks":{"a":{"a":0,"k":[0,0,0],"ix":1},"s":{"a":0,"k":[100,100,100],"ix":6},"sk":{"a":0,"k":0},"p":{"a":0,"k":[500,500,0],"ix":2},"sa":{"a":0,"k":0},"o":{"a":0,"k":100,"ix":11},"r":{"a":0,"k":0,"ix":10}},"ef":[],"shapes":[{"ty":"gr","bm":0,"cl":"","ln":"","hd":false,"mn":"ADBE Vector Group","nm":"Shape 1","ix":1,"cix":2,"np":2,"it":[{"ty":"sh","bm":0,"cl":"","ln":"","hd":false,"mn":"ADBE Vector Shape - Group","nm":"Path 1","ix":1,"d":1,"ks":{"a":0,"k":{"c":false,"i":[[0,6.938],[0,0]],"o":[[0,-5.938],[0,0]],"v":[[0.125,-257.938],[0.062,-316.25]]},"ix":2}},{"ty":"st","bm":0,"cl":"","ln":"","hd":false,"mn":"ADBE Vector Graphic - Stroke","nm":"Stroke 1","lc":2,"lj":2,"ml":1,"o":{"a":0,"k":100,"ix":4},"w":{"a":0,"k":10,"ix":5},"d":[],"c":{"a":0,"k":[0.1137,0.7255,0.2392],"ix":3}},{"ty":"tr","a":{"a":0,"k":[0,0],"ix":1},"s":{"a":0,"k":[100,100],"ix":3},"sk":{"a":0,"k":0,"ix":4},"p":{"a":0,"k":[0,0],"ix":2},"r":{"a":0,"k":0,"ix":6},"sa":{"a":0,"k":0,"ix":5},"o":{"a":0,"k":100,"ix":7}}]},{"ty":"tm","bm":0,"cl":"","ln":"","hd":false,"mn":"ADBE Vector Filter - Trim","nm":"Trim Paths 1","ix":2,"e":{"a":1,"k":[{"o":{"x":0.333,"y":0},"i":{"x":0.667,"y":1},"s":[0],"t":220},{"o":{"x":0.167,"y":0.167},"i":{"x":0.833,"y":0.833},"s":[100],"t":234.000008569907}],"ix":2},"o":{"a":0,"k":0,"ix":3},"s":{"a":0,"k":0,"ix":1},"m":1}],"ind":18},{"ty":4,"nm":"Line 20","mn":"","sr":1,"st":186.000006811978,"op":488.000017872285,"ip":225.000008240295,"hd":false,"cl":"","ln":"","ddd":0,"bm":0,"hasMask":false,"ao":0,"ks":{"a":{"a":0,"k":[0,0,0],"ix":1},"s":{"a":0,"k":[100,100,100],"ix":6},"sk":{"a":0,"k":0},"p":{"a":0,"k":[500,500,0],"ix":2},"sa":{"a":0,"k":0},"o":{"a":0,"k":100,"ix":11},"r":{"a":0,"k":0,"ix":10}},"ef":[],"shapes":[{"ty":"gr","bm":0,"cl":"","ln":"","hd":false,"mn":"ADBE Vector Group","nm":"Shape 1","ix":1,"cix":2,"np":2,"it":[{"ty":"sh","bm":0,"cl":"","ln":"","hd":false,"mn":"ADBE Vector Shape - Group","nm":"Path 1","ix":1,"d":1,"ks":{"a":0,"k":{"c":false,"i":[[0,6.938],[0,0]],"o":[[0,-5.938],[0,0]],"v":[[0.125,-257.938],[0.062,-316.25]]},"ix":2}},{"ty":"st","bm":0,"cl":"","ln":"","hd":false,"mn":"ADBE Vector Graphic - Stroke","nm":"Stroke 1","lc":2,"lj":2,"ml":1,"o":{"a":0,"k":100,"ix":4},"w":{"a":0,"k":10,"ix":5},"d":[],"c":{"a":0,"k":[0.1137,0.7255,0.2392],"ix":3}},{"ty":"tr","a":{"a":0,"k":[0,0],"ix":1},"s":{"a":0,"k":[100,100],"ix":3},"sk":{"a":0,"k":0,"ix":4},"p":{"a":0,"k":[0,0],"ix":2},"r":{"a":0,"k":0,"ix":6},"sa":{"a":0,"k":0,"ix":5},"o":{"a":0,"k":100,"ix":7}}]},{"ty":"tm","bm":0,"cl":"","ln":"","hd":false,"mn":"ADBE Vector Filter - Trim","nm":"Trim Paths 1","ix":2,"e":{"a":1,"k":[{"o":{"x":0.333,"y":0},"i":{"x":0.667,"y":1},"s":[0],"t":229},{"o":{"x":0.167,"y":0.167},"i":{"x":0.833,"y":0.833},"s":[100],"t":243.000008899519}],"ix":2},"o":{"a":0,"k":0,"ix":3},"s":{"a":0,"k":0,"ix":1},"m":1}],"ind":19},{"ty":4,"nm":"Line","mn":"","sr":1,"st":4.00000014649414,"op":306.000011206802,"ip":43.000001574812,"hd":false,"cl":"","ln":"","ddd":0,"bm":0,"hasMask":false,"ao":0,"ks":{"a":{"a":0,"k":[0,0,0],"ix":1},"s":{"a":0,"k":[100,100,100],"ix":6},"sk":{"a":0,"k":0},"p":{"a":0,"k":[500,500,0],"ix":2},"sa":{"a":0,"k":0},"o":{"a":0,"k":100,"ix":11},"r":{"a":0,"k":0,"ix":10}},"ef":[],"shapes":[{"ty":"gr","bm":0,"cl":"","ln":"","hd":false,"mn":"ADBE Vector Group","nm":"Shape 1","ix":1,"cix":2,"np":2,"it":[{"ty":"sh","bm":0,"cl":"","ln":"","hd":false,"mn":"ADBE Vector Shape - Group","nm":"Path 1","ix":1,"d":1,"ks":{"a":0,"k":{"c":false,"i":[[0,6.938],[0,0]],"o":[[0,-5.938],[0,0]],"v":[[0.125,-257.938],[0.062,-316.25]]},"ix":2}},{"ty":"st","bm":0,"cl":"","ln":"","hd":false,"mn":"ADBE Vector Graphic - Stroke","nm":"Stroke 1","lc":2,"lj":2,"ml":1,"o":{"a":0,"k":100,"ix":4},"w":{"a":0,"k":10,"ix":5},"d":[],"c":{"a":0,"k":[0.1137,0.7255,0.2392],"ix":3}},{"ty":"tr","a":{"a":0,"k":[0,0],"ix":1},"s":{"a":0,"k":[100,100],"ix":3},"sk":{"a":0,"k":0,"ix":4},"p":{"a":0,"k":[0,0],"ix":2},"r":{"a":0,"k":0,"ix":6},"sa":{"a":0,"k":0,"ix":5},"o":{"a":0,"k":100,"ix":7}}]},{"ty":"tm","bm":0,"cl":"","ln":"","hd":false,"mn":"ADBE Vector Filter - Trim","nm":"Trim Paths 1","ix":2,"e":{"a":1,"k":[{"o":{"x":0.333,"y":0},"i":{"x":0.667,"y":1},"s":[0],"t":47},{"o":{"x":0.167,"y":0.167},"i":{"x":0.833,"y":0.833},"s":[100],"t":61.0000022340356}],"ix":2},"o":{"a":0,"k":0,"ix":3},"s":{"a":0,"k":0,"ix":1},"m":1}],"ind":20},{"ty":4,"nm":"Progress","mn":"","sr":1,"st":10.0000003662354,"op":312.000011426543,"ip":10.0000003662354,"hd":false,"cl":"","ln":"","ddd":0,"bm":0,"hasMask":false,"ao":0,"ks":{"a":{"a":0,"k":[50.66,30.105,0],"ix":1},"s":{"a":0,"k":[100,100,100],"ix":6},"sk":{"a":0,"k":0},"p":{"a":0,"k":[500.062,499.997,0],"ix":2},"sa":{"a":0,"k":0},"o":{"a":0,"k":100,"ix":11},"r":{"a":0,"k":-3,"ix":10}},"ef":[],"shapes":[{"ty":"gr","bm":0,"cl":"","ln":"","hd":false,"mn":"ADBE Vector Group","nm":"Ellipse 1","ix":1,"cix":2,"np":4,"it":[{"ty":"el","bm":0,"cl":"","ln":"","hd":false,"mn":"ADBE Vector Shape - Ellipse","nm":"Ellipse Path 1","d":1,"p":{"a":0,"k":[0,0],"ix":3},"s":{"a":0,"k":[408.571,408.571],"ix":2}},{"ty":"tm","bm":0,"cl":"","ln":"","hd":false,"mn":"ADBE Vector Filter - Trim","nm":"Trim Paths 1","ix":2,"e":{"a":1,"k":[{"o":{"x":0.333,"y":0},"i":{"x":0.667,"y":1},"s":[0],"t":39},{"o":{"x":0.167,"y":0.167},"i":{"x":0.833,"y":0.833},"s":[100],"t":270.000009888354}],"ix":2},"o":{"a":0,"k":0,"ix":3},"s":{"a":1,"k":[{"o":{"x":0.333,"y":0},"i":{"x":0.667,"y":1},"s":[0],"t":39},{"o":{"x":0.167,"y":0.167},"i":{"x":0.833,"y":0.833},"s":[0],"t":270.000009888354}],"ix":1},"m":1},{"ty":"st","bm":0,"cl":"","ln":"","hd":false,"mn":"ADBE Vector Graphic - Stroke","nm":"Stroke 1","lc":2,"lj":2,"ml":1,"o":{"a":0,"k":100,"ix":4},"w":{"a":0,"k":34,"ix":5},"d":[],"c":{"a":0,"k":[0.1137,0.7255,0.2392],"ix":3}},{"ty":"tr","a":{"a":0,"k":[0,0],"ix":1},"s":{"a":0,"k":[100,100],"ix":3},"sk":{"a":0,"k":0,"ix":4},"p":{"a":0,"k":[50.597,30.105],"ix":2},"r":{"a":0,"k":0,"ix":6},"sa":{"a":0,"k":0,"ix":5},"o":{"a":0,"k":100,"ix":7}}]}],"ind":21},{"ty":3,"nm":"Barbell","mn":"","sr":1,"st":0,"op":302.000011060308,"ip":0,"hd":false,"cl":"","ln":"","ddd":0,"bm":0,"hasMask":false,"ao":0,"ks":{"a":{"a":0,"k":[0,0,0],"ix":1},"s":{"a":0,"k":[100,100,100],"ix":6},"sk":{"a":0,"k":0},"p":{"a":0,"k":[500,500,0],"ix":2},"sa":{"a":0,"k":0},"o":{"a":0,"k":0,"ix":11},"r":{"a":1,"k":[{"o":{"x":0.167,"y":0.125},"i":{"x":0.833,"y":1},"s":[0],"t":203},{"o":{"x":0.167,"y":0},"i":{"x":0.833,"y":1},"s":[-18],"t":208},{"o":{"x":0.167,"y":0},"i":{"x":0.833,"y":1},"s":[-18],"t":260},{"o":{"x":0.167,"y":0.167},"i":{"x":0.833,"y":0.833},"s":[0],"t":268.000009815107}],"ix":10}},"ef":[],"ind":22},{"ty":4,"nm":"Plate2","mn":"","sr":1,"st":221.000008093801,"op":523.000019154109,"ip":221.000008093801,"hd":false,"cl":"","ln":"","ddd":0,"bm":0,"hasMask":false,"ao":0,"ks":{"a":{"a":0,"k":[-62.75,-3.517,0],"ix":1},"s":{"a":0,"k":[100,100,100],"ix":6},"sk":{"a":0,"k":0},"p":{"a":1,"k":[{"o":{"x":0.333,"y":0},"i":{"x":0.667,"y":1},"s":[272.766,0,0],"t":221},{"o":{"x":0.167,"y":0.167},"i":{"x":0.833,"y":0.833},"s":[56.75,0,0],"t":264.000009668613}],"ix":2},"sa":{"a":0,"k":0},"o":{"a":0,"k":100,"ix":11},"r":{"a":0,"k":0,"ix":10}},"ef":[],"shapes":[{"ty":"gr","bm":0,"cl":"","ln":"","hd":false,"mn":"ADBE Vector Group","nm":"Rectangle 1","ix":1,"cix":2,"np":3,"it":[{"ty":"rc","bm":0,"cl":"","ln":"","hd":false,"mn":"ADBE Vector Shape - Rect","nm":"Rectangle Path 1","d":1,"p":{"a":0,"k":[0,0],"ix":3},"r":{"a":0,"k":20,"ix":4},"s":{"a":0,"k":[39.736,156.123],"ix":2}},{"ty":"st","bm":0,"cl":"","ln":"","hd":false,"mn":"ADBE Vector Graphic - Stroke","nm":"Stroke 1","lc":1,"lj":1,"ml":4,"o":{"a":0,"k":100,"ix":4},"w":{"a":0,"k":28,"ix":5},"d":[],"c":{"a":0,"k":[0.1137,0.7255,0.2392],"ix":3}},{"ty":"fl","bm":0,"cl":"","ln":"","hd":false,"mn":"ADBE Vector Graphic - Fill","nm":"Fill 1","c":{"a":0,"k":[1,1,1],"ix":4},"r":1,"o":{"a":0,"k":100,"ix":5}},{"ty":"tr","a":{"a":0,"k":[0,0],"ix":1},"s":{"a":0,"k":[85.644,94.889],"ix":3},"sk":{"a":0,"k":0,"ix":4},"p":{"a":0,"k":[-62.835,-3.517],"ix":2},"r":{"a":0,"k":0,"ix":6},"sa":{"a":0,"k":0,"ix":5},"o":{"a":0,"k":100,"ix":7}}]}],"ind":23,"parent":22},{"ty":4,"nm":"pop6","mn":"","sr":1,"st":62.0000022706592,"op":364.000013330967,"ip":242.000008862896,"hd":false,"cl":"","ln":"","ddd":0,"bm":0,"hasMask":false,"ao":0,"ks":{"a":{"a":0,"k":[0,0,0],"ix":1},"s":{"a":0,"k":[100,100,100],"ix":6},"sk":{"a":0,"k":0},"p":{"a":0,"k":[0,0,0],"ix":2},"sa":{"a":0,"k":0},"o":{"a":0,"k":100,"ix":11},"r":{"a":0,"k":183.933,"ix":10}},"ef":[],"shapes":[{"ty":"gr","bm":0,"cl":"","ln":"","hd":false,"mn":"ADBE Vector Group","nm":"Shape 1","ix":1,"cix":2,"np":3,"it":[{"ty":"sh","bm":0,"cl":"","ln":"","hd":false,"mn":"ADBE Vector Shape - Group","nm":"Path 1","ix":1,"d":1,"ks":{"a":0,"k":{"c":false,"i":[[0,0],[0,0]],"o":[[0,0],[0,0]],"v":[[-103,41],[-140,78]]},"ix":2}},{"ty":"st","bm":0,"cl":"","ln":"","hd":false,"mn":"ADBE Vector Graphic - Stroke","nm":"Stroke 1","lc":2,"lj":1,"ml":4,"o":{"a":0,"k":100,"ix":4},"w":{"a":0,"k":5,"ix":5},"d":[],"c":{"a":0,"k":[0.1137,0.7255,0.2392],"ix":3}},{"ty":"fl","bm":0,"cl":"","ln":"","hd":false,"mn":"ADBE Vector Graphic - Fill","nm":"Fill 1","c":{"a":0,"k":[0.1059,0.2902,0.8],"ix":4},"r":1,"o":{"a":0,"k":100,"ix":5}},{"ty":"tr","a":{"a":0,"k":[0,0],"ix":1},"s":{"a":0,"k":[100,100],"ix":3},"sk":{"a":0,"k":0,"ix":4},"p":{"a":0,"k":[0,0],"ix":2},"r":{"a":0,"k":0,"ix":6},"sa":{"a":0,"k":0,"ix":5},"o":{"a":0,"k":100,"ix":7}}]},{"ty":"tm","bm":0,"cl":"","ln":"","hd":false,"mn":"ADBE Vector Filter - Trim","nm":"Trim Paths 1","ix":2,"e":{"a":1,"k":[{"o":{"x":0.333,"y":0},"i":{"x":0.667,"y":1},"s":[0],"t":252},{"o":{"x":0.167,"y":0.167},"i":{"x":0.833,"y":0.833},"s":[100],"t":269.000009851731}],"ix":2},"o":{"a":0,"k":0,"ix":3},"s":{"a":1,"k":[{"o":{"x":0.333,"y":0},"i":{"x":0.667,"y":1},"s":[0],"t":247},{"o":{"x":0.167,"y":0.167},"i":{"x":0.833,"y":0.833},"s":[100],"t":264.000009668613}],"ix":1},"m":1}],"ind":24,"parent":22},{"ty":4,"nm":"pop5","mn":"","sr":1,"st":247.000009046013,"op":549.000020106321,"ip":247.000009046013,"hd":false,"cl":"","ln":"","ddd":0,"bm":0,"hasMask":false,"ao":0,"ks":{"a":{"a":0,"k":[0,0,0],"ix":1},"s":{"a":0,"k":[100,100,100],"ix":6},"sk":{"a":0,"k":0},"p":{"a":0,"k":[0,0,0],"ix":2},"sa":{"a":0,"k":0},"o":{"a":0,"k":100,"ix":11},"r":{"a":0,"k":183.933,"ix":10}},"ef":[],"shapes":[{"ty":"gr","bm":0,"cl":"","ln":"","hd":false,"mn":"ADBE Vector Group","nm":"Shape 1","ix":1,"cix":2,"np":3,"it":[{"ty":"sh","bm":0,"cl":"","ln":"","hd":false,"mn":"ADBE Vector Shape - Group","nm":"Path 1","ix":1,"d":1,"ks":{"a":0,"k":{"c":false,"i":[[1.062,0],[0,0]],"o":[[-1,0],[0,0]],"v":[[-123.75,0],[-165,0]]},"ix":2}},{"ty":"st","bm":0,"cl":"","ln":"","hd":false,"mn":"ADBE Vector Graphic - Stroke","nm":"Stroke 1","lc":1,"lj":1,"ml":4,"o":{"a":0,"k":100,"ix":4},"w":{"a":0,"k":5,"ix":5},"d":[],"c":{"a":0,"k":[0.1137,0.7255,0.2392],"ix":3}},{"ty":"fl","bm":0,"cl":"","ln":"","hd":false,"mn":"ADBE Vector Graphic - Fill","nm":"Fill 1","c":{"a":0,"k":[0.1059,0.2902,0.8],"ix":4},"r":1,"o":{"a":0,"k":100,"ix":5}},{"ty":"tr","a":{"a":0,"k":[0,0],"ix":1},"s":{"a":0,"k":[100,100],"ix":3},"sk":{"a":0,"k":0,"ix":4},"p":{"a":0,"k":[0,0],"ix":2},"r":{"a":0,"k":0,"ix":6},"sa":{"a":0,"k":0,"ix":5},"o":{"a":0,"k":100,"ix":7}}]},{"ty":"tm","bm":0,"cl":"","ln":"","hd":false,"mn":"ADBE Vector Filter - Trim","nm":"Trim Paths 1","ix":2,"e":{"a":1,"k":[{"o":{"x":0.333,"y":0},"i":{"x":0.667,"y":1},"s":[0],"t":252},{"o":{"x":0.167,"y":0.167},"i":{"x":0.833,"y":0.833},"s":[100],"t":269.000009851731}],"ix":2},"o":{"a":0,"k":0,"ix":3},"s":{"a":1,"k":[{"o":{"x":0.333,"y":0},"i":{"x":0.667,"y":1},"s":[0],"t":247},{"o":{"x":0.167,"y":0.167},"i":{"x":0.833,"y":0.833},"s":[100],"t":264.000009668613}],"ix":1},"m":1}],"ind":25,"parent":22},{"ty":4,"nm":"pop4","mn":"","sr":1,"st":247.000009046013,"op":549.000020106321,"ip":247.000009046013,"hd":false,"cl":"","ln":"","ddd":0,"bm":0,"hasMask":false,"ao":0,"ks":{"a":{"a":0,"k":[0,0,0],"ix":1},"s":{"a":0,"k":[100,100,100],"ix":6},"sk":{"a":0,"k":0},"p":{"a":0,"k":[0,0,0],"ix":2},"sa":{"a":0,"k":0},"o":{"a":0,"k":100,"ix":11},"r":{"a":0,"k":183.933,"ix":10}},"ef":[],"shapes":[{"ty":"gr","bm":0,"cl":"","ln":"","hd":false,"mn":"ADBE Vector Group","nm":"Shape 1","ix":1,"cix":2,"np":4,"it":[{"ty":"sh","bm":0,"cl":"","ln":"","hd":false,"mn":"ADBE Vector Shape - Group","nm":"Path 1","ix":1,"d":1,"ks":{"a":0,"k":{"c":false,"i":[[0,0],[0,0]],"o":[[0,0],[0,0]],"v":[[-106,-28],[-128,-50]]},"ix":2}},{"ty":"tm","bm":0,"cl":"","ln":"","hd":false,"mn":"ADBE Vector Filter - Trim","nm":"Trim Paths 1","ix":2,"e":{"a":0,"k":100,"ix":2},"o":{"a":0,"k":0,"ix":3},"s":{"a":0,"k":0,"ix":1},"m":1},{"ty":"st","bm":0,"cl":"","ln":"","hd":false,"mn":"ADBE Vector Graphic - Stroke","nm":"Stroke 1","lc":2,"lj":2,"ml":1,"o":{"a":0,"k":100,"ix":4},"w":{"a":0,"k":5,"ix":5},"d":[],"c":{"a":0,"k":[0.1137,0.7255,0.2392],"ix":3}},{"ty":"fl","bm":0,"cl":"","ln":"","hd":false,"mn":"ADBE Vector Graphic - Fill","nm":"Fill 1","c":{"a":0,"k":[0.1059,0.2902,0.8],"ix":4},"r":1,"o":{"a":0,"k":100,"ix":5}},{"ty":"tr","a":{"a":0,"k":[0,0],"ix":1},"s":{"a":0,"k":[100,100],"ix":3},"sk":{"a":0,"k":0,"ix":4},"p":{"a":0,"k":[0,0],"ix":2},"r":{"a":0,"k":0,"ix":6},"sa":{"a":0,"k":0,"ix":5},"o":{"a":0,"k":100,"ix":7}}]},{"ty":"tm","bm":0,"cl":"","ln":"","hd":false,"mn":"ADBE Vector Filter - Trim","nm":"Trim Paths 1","ix":2,"e":{"a":0,"k":100,"ix":2},"o":{"a":0,"k":0,"ix":3},"s":{"a":0,"k":0,"ix":1},"m":1},{"ty":"tm","bm":0,"cl":"","ln":"","hd":false,"mn":"ADBE Vector Filter - Trim","nm":"Trim Paths 2","ix":3,"e":{"a":1,"k":[{"o":{"x":0.333,"y":0},"i":{"x":0.667,"y":1},"s":[0],"t":252},{"o":{"x":0.167,"y":0.167},"i":{"x":0.833,"y":0.833},"s":[100],"t":269.000009851731}],"ix":2},"o":{"a":0,"k":0,"ix":3},"s":{"a":1,"k":[{"o":{"x":0.333,"y":0},"i":{"x":0.667,"y":1},"s":[0],"t":247},{"o":{"x":0.167,"y":0.167},"i":{"x":0.833,"y":0.833},"s":[100],"t":264.000009668613}],"ix":1},"m":1}],"ind":26,"parent":22},{"ty":4,"nm":"pop3","mn":"","sr":1,"st":197.000007214836,"op":499.000018275144,"ip":197.000007214836,"hd":false,"cl":"","ln":"","ddd":0,"bm":0,"hasMask":false,"ao":0,"ks":{"a":{"a":0,"k":[0,0,0],"ix":1},"s":{"a":0,"k":[100,100,100],"ix":6},"sk":{"a":0,"k":0},"p":{"a":0,"k":[0,0,0],"ix":2},"sa":{"a":0,"k":0},"o":{"a":0,"k":100,"ix":11},"r":{"a":0,"k":0,"ix":10}},"ef":[],"shapes":[{"ty":"gr","bm":0,"cl":"","ln":"","hd":false,"mn":"ADBE Vector Group","nm":"Shape 1","ix":1,"cix":2,"np":4,"it":[{"ty":"sh","bm":0,"cl":"","ln":"","hd":false,"mn":"ADBE Vector Shape - Group","nm":"Path 1","ix":1,"d":1,"ks":{"a":0,"k":{"c":false,"i":[[0,0],[0,0]],"o":[[0,0],[0,0]],"v":[[-106,-28],[-128,-50]]},"ix":2}},{"ty":"tm","bm":0,"cl":"","ln":"","hd":false,"mn":"ADBE Vector Filter - Trim","nm":"Trim Paths 1","ix":2,"e":{"a":0,"k":100,"ix":2},"o":{"a":0,"k":0,"ix":3},"s":{"a":0,"k":0,"ix":1},"m":1},{"ty":"st","bm":0,"cl":"","ln":"","hd":false,"mn":"ADBE Vector Graphic - Stroke","nm":"Stroke 1","lc":2,"lj":2,"ml":1,"o":{"a":0,"k":100,"ix":4},"w":{"a":0,"k":5,"ix":5},"d":[],"c":{"a":0,"k":[0.1137,0.7255,0.2392],"ix":3}},{"ty":"fl","bm":0,"cl":"","ln":"","hd":false,"mn":"ADBE Vector Graphic - Fill","nm":"Fill 1","c":{"a":0,"k":[0.1059,0.2902,0.8],"ix":4},"r":1,"o":{"a":0,"k":100,"ix":5}},{"ty":"tr","a":{"a":0,"k":[0,0],"ix":1},"s":{"a":0,"k":[100,100],"ix":3},"sk":{"a":0,"k":0,"ix":4},"p":{"a":0,"k":[0,0],"ix":2},"r":{"a":0,"k":0,"ix":6},"sa":{"a":0,"k":0,"ix":5},"o":{"a":0,"k":100,"ix":7}}]},{"ty":"tm","bm":0,"cl":"","ln":"","hd":false,"mn":"ADBE Vector Filter - Trim","nm":"Trim Paths 1","ix":2,"e":{"a":0,"k":100,"ix":2},"o":{"a":0,"k":0,"ix":3},"s":{"a":0,"k":0,"ix":1},"m":1},{"ty":"tm","bm":0,"cl":"","ln":"","hd":false,"mn":"ADBE Vector Filter - Trim","nm":"Trim Paths 2","ix":3,"e":{"a":1,"k":[{"o":{"x":0.333,"y":0},"i":{"x":0.667,"y":1},"s":[0],"t":202},{"o":{"x":0.167,"y":0.167},"i":{"x":0.833,"y":0.833},"s":[100],"t":219.000008020554}],"ix":2},"o":{"a":0,"k":0,"ix":3},"s":{"a":1,"k":[{"o":{"x":0.333,"y":0},"i":{"x":0.667,"y":1},"s":[0],"t":197},{"o":{"x":0.167,"y":0.167},"i":{"x":0.833,"y":0.833},"s":[100],"t":214.000007837437}],"ix":1},"m":1}],"ind":27,"parent":22},{"ty":4,"nm":"pop2","mn":"","sr":1,"st":197.000007214836,"op":499.000018275144,"ip":197.000007214836,"hd":false,"cl":"","ln":"","ddd":0,"bm":0,"hasMask":false,"ao":0,"ks":{"a":{"a":0,"k":[0,0,0],"ix":1},"s":{"a":0,"k":[100,100,100],"ix":6},"sk":{"a":0,"k":0},"p":{"a":0,"k":[0,0,0],"ix":2},"sa":{"a":0,"k":0},"o":{"a":0,"k":100,"ix":11},"r":{"a":0,"k":0,"ix":10}},"ef":[],"shapes":[{"ty":"gr","bm":0,"cl":"","ln":"","hd":false,"mn":"ADBE Vector Group","nm":"Shape 1","ix":1,"cix":2,"np":3,"it":[{"ty":"sh","bm":0,"cl":"","ln":"","hd":false,"mn":"ADBE Vector Shape - Group","nm":"Path 1","ix":1,"d":1,"ks":{"a":0,"k":{"c":false,"i":[[1.062,0],[0,0]],"o":[[-1,0],[0,0]],"v":[[-123.75,0],[-165,0]]},"ix":2}},{"ty":"st","bm":0,"cl":"","ln":"","hd":false,"mn":"ADBE Vector Graphic - Stroke","nm":"Stroke 1","lc":1,"lj":1,"ml":4,"o":{"a":0,"k":100,"ix":4},"w":{"a":0,"k":5,"ix":5},"d":[],"c":{"a":0,"k":[0.1137,0.7255,0.2392],"ix":3}},{"ty":"fl","bm":0,"cl":"","ln":"","hd":false,"mn":"ADBE Vector Graphic - Fill","nm":"Fill 1","c":{"a":0,"k":[0.1059,0.2902,0.8],"ix":4},"r":1,"o":{"a":0,"k":100,"ix":5}},{"ty":"tr","a":{"a":0,"k":[0,0],"ix":1},"s":{"a":0,"k":[100,100],"ix":3},"sk":{"a":0,"k":0,"ix":4},"p":{"a":0,"k":[0,0],"ix":2},"r":{"a":0,"k":0,"ix":6},"sa":{"a":0,"k":0,"ix":5},"o":{"a":0,"k":100,"ix":7}}]},{"ty":"tm","bm":0,"cl":"","ln":"","hd":false,"mn":"ADBE Vector Filter - Trim","nm":"Trim Paths 1","ix":2,"e":{"a":1,"k":[{"o":{"x":0.333,"y":0},"i":{"x":0.667,"y":1},"s":[0],"t":202},{"o":{"x":0.167,"y":0.167},"i":{"x":0.833,"y":0.833},"s":[100],"t":219.000008020554}],"ix":2},"o":{"a":0,"k":0,"ix":3},"s":{"a":1,"k":[{"o":{"x":0.333,"y":0},"i":{"x":0.667,"y":1},"s":[0],"t":197},{"o":{"x":0.167,"y":0.167},"i":{"x":0.833,"y":0.833},"s":[100],"t":214.000007837437}],"ix":1},"m":1}],"ind":28,"parent":22},{"ty":4,"nm":"pop1","mn":"","sr":1,"st":12.0000004394824,"op":314.00001149979,"ip":192.000007031719,"hd":false,"cl":"","ln":"","ddd":0,"bm":0,"hasMask":false,"ao":0,"ks":{"a":{"a":0,"k":[0,0,0],"ix":1},"s":{"a":0,"k":[100,100,100],"ix":6},"sk":{"a":0,"k":0},"p":{"a":0,"k":[0,0,0],"ix":2},"sa":{"a":0,"k":0},"o":{"a":0,"k":100,"ix":11},"r":{"a":0,"k":0,"ix":10}},"ef":[],"shapes":[{"ty":"gr","bm":0,"cl":"","ln":"","hd":false,"mn":"ADBE Vector Group","nm":"Shape 1","ix":1,"cix":2,"np":3,"it":[{"ty":"sh","bm":0,"cl":"","ln":"","hd":false,"mn":"ADBE Vector Shape - Group","nm":"Path 1","ix":1,"d":1,"ks":{"a":0,"k":{"c":false,"i":[[0,0],[0,0]],"o":[[0,0],[0,0]],"v":[[-103,41],[-140,78]]},"ix":2}},{"ty":"st","bm":0,"cl":"","ln":"","hd":false,"mn":"ADBE Vector Graphic - Stroke","nm":"Stroke 1","lc":2,"lj":1,"ml":4,"o":{"a":0,"k":100,"ix":4},"w":{"a":0,"k":5,"ix":5},"d":[],"c":{"a":0,"k":[0.1137,0.7255,0.2392],"ix":3}},{"ty":"fl","bm":0,"cl":"","ln":"","hd":false,"mn":"ADBE Vector Graphic - Fill","nm":"Fill 1","c":{"a":0,"k":[0.1059,0.2902,0.8],"ix":4},"r":1,"o":{"a":0,"k":100,"ix":5}},{"ty":"tr","a":{"a":0,"k":[0,0],"ix":1},"s":{"a":0,"k":[100,100],"ix":3},"sk":{"a":0,"k":0,"ix":4},"p":{"a":0,"k":[0,0],"ix":2},"r":{"a":0,"k":0,"ix":6},"sa":{"a":0,"k":0,"ix":5},"o":{"a":0,"k":100,"ix":7}}]},{"ty":"tm","bm":0,"cl":"","ln":"","hd":false,"mn":"ADBE Vector Filter - Trim","nm":"Trim Paths 1","ix":2,"e":{"a":1,"k":[{"o":{"x":0.333,"y":0},"i":{"x":0.667,"y":1},"s":[0],"t":202},{"o":{"x":0.167,"y":0.167},"i":{"x":0.833,"y":0.833},"s":[100],"t":219.000008020554}],"ix":2},"o":{"a":0,"k":0,"ix":3},"s":{"a":1,"k":[{"o":{"x":0.333,"y":0},"i":{"x":0.667,"y":1},"s":[0],"t":197},{"o":{"x":0.167,"y":0.167},"i":{"x":0.833,"y":0.833},"s":[100],"t":214.000007837437}],"ix":1},"m":1}],"ind":29,"parent":22},{"ty":4,"nm":"Plate1","mn":"","sr":1,"st":180.000006592236,"op":482.000017652544,"ip":180.000006592236,"hd":false,"cl":"","ln":"","ddd":0,"bm":0,"hasMask":false,"ao":0,"ks":{"a":{"a":0,"k":[-62.812,-3.517,0],"ix":1},"s":{"a":0,"k":[100,100,100],"ix":6},"sk":{"a":0,"k":0},"p":{"a":1,"k":[{"o":{"x":0.333,"y":0},"i":{"x":0.667,"y":0.807},"s":[-275.312,0,0],"t":180},{"o":{"x":0.224,"y":1},"i":{"x":0.667,"y":1},"s":[-55.139,0,0],"t":206},{"o":{"x":0.167,"y":0.167},"i":{"x":0.833,"y":0.833},"s":[-55.812,0,0],"t":210.000007690942}],"ix":2},"sa":{"a":0,"k":0},"o":{"a":0,"k":100,"ix":11},"r":{"a":0,"k":0,"ix":10}},"ef":[],"shapes":[{"ty":"gr","bm":0,"cl":"","ln":"","hd":false,"mn":"ADBE Vector Group","nm":"Rectangle 1","ix":1,"cix":2,"np":3,"it":[{"ty":"rc","bm":0,"cl":"","ln":"","hd":false,"mn":"ADBE Vector Shape - Rect","nm":"Rectangle Path 1","d":1,"p":{"a":0,"k":[0,0],"ix":3},"r":{"a":0,"k":20,"ix":4},"s":{"a":0,"k":[39.736,156.123],"ix":2}},{"ty":"st","bm":0,"cl":"","ln":"","hd":false,"mn":"ADBE Vector Graphic - Stroke","nm":"Stroke 1","lc":1,"lj":1,"ml":4,"o":{"a":0,"k":100,"ix":4},"w":{"a":0,"k":28,"ix":5},"d":[],"c":{"a":0,"k":[0.1137,0.7255,0.2392],"ix":3}},{"ty":"fl","bm":0,"cl":"","ln":"","hd":false,"mn":"ADBE Vector Graphic - Fill","nm":"Fill 1","c":{"a":0,"k":[1,1,1],"ix":4},"r":1,"o":{"a":0,"k":100,"ix":5}},{"ty":"tr","a":{"a":0,"k":[0,0],"ix":1},"s":{"a":0,"k":[85.644,94.889],"ix":3},"sk":{"a":0,"k":0,"ix":4},"p":{"a":0,"k":[-62.835,-3.517],"ix":2},"r":{"a":0,"k":0,"ix":6},"sa":{"a":0,"k":0,"ix":5},"o":{"a":0,"k":100,"ix":7}}]}],"ind":30,"parent":22},{"ty":4,"nm":"Bar","mn":"","sr":1,"st":40.0000014649414,"op":342.000012525249,"ip":40.0000014649414,"hd":false,"cl":"","ln":"","ddd":0,"bm":0,"hasMask":false,"ao":0,"ks":{"a":{"a":0,"k":[-3.572,-18.971,0],"ix":1},"s":{"a":1,"k":[{"o":{"x":0.333,"y":0},"i":{"x":0.667,"y":1},"s":[0,0,100],"t":40},{"o":{"x":0.333,"y":0},"i":{"x":0.833,"y":1},"s":[100,100,100],"t":66},{"o":{"x":0.167,"y":0.167},"i":{"x":0.833,"y":0.833},"s":[91.238,100,100],"t":90.0000032961182}],"ix":6},"sk":{"a":0,"k":0},"p":{"a":0,"k":[0.062,0,0],"ix":2},"sa":{"a":0,"k":0},"o":{"a":0,"k":100,"ix":11},"r":{"a":0,"k":0,"ix":10}},"ef":[],"shapes":[{"ty":"gr","bm":0,"cl":"","ln":"","hd":false,"mn":"ADBE Vector Group","nm":"Rectangle 1","ix":1,"cix":2,"np":3,"it":[{"ty":"rc","bm":0,"cl":"","ln":"","hd":false,"mn":"ADBE Vector Shape - Rect","nm":"Rectangle Path 1","d":1,"p":{"a":0,"k":[0,0],"ix":3},"r":{"a":0,"k":20,"ix":4},"s":{"a":1,"k":[{"o":{"x":0.167,"y":0.167},"i":{"x":0.833,"y":0.833},"s":[42.2,42.2],"t":90},{"o":{"x":0.167,"y":0.167},"i":{"x":0.833,"y":0.833},"s":[235.816,42.219],"t":139.000005090671}],"ix":2}},{"ty":"st","bm":0,"cl":"","ln":"","hd":false,"mn":"ADBE Vector Graphic - Stroke","nm":"Stroke 1","lc":1,"lj":1,"ml":4,"o":{"a":0,"k":100,"ix":4},"w":{"a":0,"k":29,"ix":5},"d":[],"c":{"a":0,"k":[0.1137,0.7255,0.2392],"ix":3}},{"ty":"tr","a":{"a":0,"k":[0,0],"ix":1},"s":{"a":0,"k":[94.958,83.785],"ix":3},"sk":{"a":0,"k":0,"ix":4},"p":{"a":0,"k":[-3.635,-18.971],"ix":2},"r":{"a":0,"k":0,"ix":6},"sa":{"a":0,"k":0,"ix":5},"o":{"a":0,"k":100,"ix":7}}]}],"ind":31,"parent":22},{"ty":4,"nm":"OutterRim","mn":"","sr":1,"st":10.0000003662354,"op":312.000011426543,"ip":10.0000003662354,"hd":false,"cl":"","ln":"","ddd":0,"bm":0,"hasMask":false,"ao":0,"ks":{"a":{"a":0,"k":[50.66,30.105,0],"ix":1},"s":{"a":1,"k":[{"o":{"x":0.333,"y":0},"i":{"x":0.667,"y":1},"s":[0,0,100],"t":10},{"o":{"x":0.333,"y":0},"i":{"x":0.667,"y":1},"s":[120,120,100],"t":30},{"o":{"x":0.167,"y":0.167},"i":{"x":0.833,"y":0.833},"s":[100,100,100],"t":35.0000012818237}],"ix":6},"sk":{"a":0,"k":0},"p":{"a":0,"k":[500.062,500,0],"ix":2},"sa":{"a":0,"k":0},"o":{"a":0,"k":100,"ix":11},"r":{"a":0,"k":0,"ix":10}},"ef":[],"shapes":[{"ty":"gr","bm":0,"cl":"","ln":"","hd":false,"mn":"ADBE Vector Group","nm":"Ellipse 1","ix":1,"cix":2,"np":3,"it":[{"ty":"el","bm":0,"cl":"","ln":"","hd":false,"mn":"ADBE Vector Shape - Ellipse","nm":"Ellipse Path 1","d":1,"p":{"a":0,"k":[0,0],"ix":3},"s":{"a":0,"k":[408.571,408.571],"ix":2}},{"ty":"st","bm":0,"cl":"","ln":"","hd":false,"mn":"ADBE Vector Graphic - Stroke","nm":"Stroke 1","lc":1,"lj":1,"ml":4,"o":{"a":0,"k":100,"ix":4},"w":{"a":0,"k":34,"ix":5},"d":[],"c":{"a":0,"k":[0.8353,0.8392,0.8745],"ix":3}},{"ty":"tr","a":{"a":0,"k":[0,0],"ix":1},"s":{"a":0,"k":[100,100],"ix":3},"sk":{"a":0,"k":0,"ix":4},"p":{"a":0,"k":[50.597,30.105],"ix":2},"r":{"a":0,"k":0,"ix":6},"sa":{"a":0,"k":0,"ix":5},"o":{"a":0,"k":100,"ix":7}}]}],"ind":32}],"ddd":0,"h":1000,"w":1000,"meta":{"a":"","k":"","d":"","g":"@lottiefiles/toolkit-js 0.21.3","tc":"#000000"},"v":"5.6.5","fr":59.9960021972656,"op":302.000011060308,"ip":0,"assets":[]}